archive_query_log/__init__.py
archive_query_log/__main__.py
archive_query_log/config.py
archive_query_log/namespaces.py
archive_query_log/orm.py
archive_query_log/archives/__init__.py
archive_query_log/captures/__init__.py
archive_query_log/cli/__init__.py
archive_query_log/cli/archives.py
archive_query_log/cli/captures.py
archive_query_log/cli/monitoring.py
archive_query_log/cli/parsers.py
archive_query_log/cli/providers.py
archive_query_log/cli/serps.py
archive_query_log/cli/sources.py
archive_query_log/cli/util.py
archive_query_log/downloaders/__init__.py
archive_query_log/downloaders/warc.py
archive_query_log/imports/__init__.py
archive_query_log/imports/aql22.py
archive_query_log/imports/archive_it.py
archive_query_log/imports/yaml.py
archive_query_log/legacy/__init__.py
archive_query_log/legacy/config.py
archive_query_log/legacy/conftest.py
archive_query_log/legacy/generate_review_sample.py
archive_query_log/legacy/service_stats.py
archive_query_log/legacy/cli/__init__.py
archive_query_log/legacy/cli/alexa.py
archive_query_log/legacy/cli/corpus.py
archive_query_log/legacy/cli/external.py
archive_query_log/legacy/cli/index.py
archive_query_log/legacy/cli/make.py
archive_query_log/legacy/cli/util.py
archive_query_log/legacy/download/__init__.py
archive_query_log/legacy/download/iterable.py
archive_query_log/legacy/download/raw.py
archive_query_log/legacy/download/warc.py
archive_query_log/legacy/index/__init__.py
archive_query_log/legacy/model/__init__.py
archive_query_log/legacy/model/highlight.py
archive_query_log/legacy/model/parse.py
archive_query_log/legacy/queries/__init__.py
archive_query_log/legacy/queries/iterable.py
archive_query_log/legacy/queries/parse.py
archive_query_log/legacy/results/__init__.py
archive_query_log/legacy/results/chatnoir.py
archive_query_log/legacy/results/parse.py
archive_query_log/legacy/results/test/__init__.py
archive_query_log/legacy/results/test/generate_tests.py
archive_query_log-1.2.26.dist-info/LICENSE
archive_query_log-1.2.26.dist-info/METADATA
archive_query_log-1.2.26.dist-info/WHEEL
archive_query_log-1.2.26.dist-info/entry_points.txt
archive_query_log-1.2.26.dist-info/top_level.txt
archive_query_log-1.2.26.dist-info/RECORD
