Metadata-Version: 2.1
Name: archive-query-log
Version: 1.2.26
Summary: Mining Millions of Search Result Pages of Hundreds of Search Engines from 25 Years of Web Archives.
Author-email: Jan Heinrich Reimer <heinrich.reimer@uni-jena.de>, Sebastian Schmidt <s.schmidt@uni-leipzig.de>, Maik Fröbe <maik.froebe@uni-jena.de>, Lukas Gienapp <lukas.gienapp@uni-leipzig.de>, Harrisen Scells <harry.scells@uni-leipzig.de>, Benno Stein <benno.stein@uni-weimar.de>, Matthias Hagen <matthias.hagen@uni-jena.de>, Martin Potthast <martin.potthast@uni-leipzig.de>
Project-URL: Homepage, https://github.com/webis-de/archive-query-log
Project-URL: Bug Tracker, https://github.com/webis-de/archive-query-log/issues
Classifier: Programming Language :: Python :: 3
Classifier: Programming Language :: Python :: 3 :: Only
Classifier: Programming Language :: Python :: 3.10
Classifier: Programming Language :: Python :: 3.11
Classifier: Operating System :: OS Independent
Classifier: Intended Audience :: Science/Research
Classifier: Topic :: Scientific/Engineering
Requires-Python: >=3.10
License-File: LICENSE
Requires-Dist: aiohttp ~=3.8
Requires-Dist: aiohttp-retry ~=2.8
Requires-Dist: asyncio-pool ~=0.6.0
Requires-Dist: beautifulsoup4 ~=4.12
Requires-Dist: bleach ~=6.0
Requires-Dist: boto3 ~=1.28
Requires-Dist: certifi ~=2023.7
Requires-Dist: click ~=8.1
Requires-Dist: cssselect ~=1.2
Requires-Dist: dataclasses-json ~=0.6.0
Requires-Dist: diskcache ~=5.6
Requires-Dist: elasticsearch ~=7.0
Requires-Dist: elasticsearch-dsl ~=7.0
Requires-Dist: expiringdict ~=1.2
Requires-Dist: flask ~=2.3
Requires-Dist: importlib-metadata ~=6.0
Requires-Dist: joblib ~=1.3
Requires-Dist: lxml ~=4.9
Requires-Dist: marshmallow ~=3.20
Requires-Dist: mergedeep ~=1.3
Requires-Dist: more-itertools ~=10.1
Requires-Dist: pandas ~=2.0
Requires-Dist: publicsuffixlist ~=0.10.0
Requires-Dist: pycld3 ~=0.22.0
Requires-Dist: python-slugify ~=8.0
Requires-Dist: python-whois ~=0.8.0
Requires-Dist: pyyaml ~=6.0
Requires-Dist: ranx ~=0.3.16
Requires-Dist: requests ~=2.31
Requires-Dist: requests-html ~=0.10.0
Requires-Dist: requests-ratelimiter ~=0.4.0
Requires-Dist: tqdm ~=4.66
Requires-Dist: unidecode ~=1.3
Requires-Dist: urllib3 ~=1.26
Requires-Dist: warcio ~=1.7
Requires-Dist: warc-s3 ~=0.1.1
Requires-Dist: web-archive-api ~=0.1.6
Provides-Extra: examples
Requires-Dist: jupyter ~=1.0 ; extra == 'examples'
Requires-Dist: matplotlib ~=3.7 ; extra == 'examples'
Requires-Dist: seaborn ~=0.13.0 ; extra == 'examples'
Provides-Extra: tests
Requires-Dist: approvaltests ~=10.0 ; extra == 'tests'
Requires-Dist: bandit[toml] ~=1.7 ; extra == 'tests'
Requires-Dist: boto3-stubs[s3] ~=1.28 ; extra == 'tests'
Requires-Dist: flake8 ~=6.1 ; extra == 'tests'
Requires-Dist: mypy ~=1.5 ; extra == 'tests'
Requires-Dist: pandas-stubs ~=2.0 ; extra == 'tests'
Requires-Dist: pylint ~=2.17 ; extra == 'tests'
Requires-Dist: pytest ~=7.4 ; extra == 'tests'
Requires-Dist: pytest-cov ~=4.0 ; extra == 'tests'
Requires-Dist: types-beautifulsoup4 ~=4.12 ; extra == 'tests'
Requires-Dist: types-bleach ~=6.0 ; extra == 'tests'
Requires-Dist: types-lxml ~=2023.10 ; extra == 'tests'
Requires-Dist: types-python-dateutil ~=2.8 ; extra == 'tests'
Requires-Dist: types-python-slugify ~=8.0 ; extra == 'tests'
Requires-Dist: types-pyyaml ~=6.0 ; extra == 'tests'
Requires-Dist: types-requests ~=2.31 ; extra == 'tests'
Requires-Dist: types-tqdm ~=4.66 ; extra == 'tests'
